nested_config/__init__.py
nested_config/_pydantic.py
nested_config/_types.py
nested_config/expand.py
nested_config/loaders.py
nested_config/py.typed
nested_config/version.py
nested_config-2.1.4.dist-info/METADATA
nested_config-2.1.4.dist-info/WHEEL
nested_config-2.1.4.dist-info/licenses/LICENSE
nested_config-2.1.4.dist-info/RECORD
