Metadata-Version: 2.4
Name: nested-config
Version: 2.1.4
Summary: Parse configuration files that include paths to other config files into a single configuration object
Project-URL: Repository, https://gitlab.com/osu-nrsg/nested-config
Project-URL: Issues, https://gitlab.com/osu-nrsg/nested-config/-/issues
Project-URL: Changelog, https://gitlab.com/osu-nrsg/nested-config/-/blob/master/CHANGELOG.md
Project-URL: GitHub Mirror, https://github.com/RandallPittmanOrSt/nested-config
Author-email: Randall Pittman <pittmara@oregonstate.edu>
License-Expression: MIT
License-File: LICENSE
Keywords: config,configuration files
Classifier: Development Status :: 5 - Production/Stable
Classifier: Intended Audience :: Developers
Classifier: License :: OSI Approved :: MIT License
Classifier: Programming Language :: Python :: 3.8
Classifier: Programming Language :: Python :: 3.9
Classifier: Programming Language :: Python :: 3.10
Classifier: Programming Language :: Python :: 3.11
Classifier: Programming Language :: Python :: 3.12
Requires-Python: >=3.8
Requires-Dist: packaging>=24.2
Requires-Dist: pydantic<3.0.0,>=1.8
Requires-Dist: single-version>=1.6.0
Requires-Dist: tomli>=2.0.0; python_version < '3.11'
Requires-Dist: typing-extensions>=4.6.0
Provides-Extra: pydantic
Requires-Dist: pydantic>=1.8; extra == 'pydantic'
Provides-Extra: pyyaml
Requires-Dist: pyyaml>=5.1.0; extra == 'pyyaml'
